{
  "site": {
    "title": "☕ Кофе и Чай - Лучшие напитки в Бишкек",
    "description": "Насладитесь лучшим кофе, чаем и матча в городе Бишкек. Свежеобжаренные зерна, авторские рецепты и уютная атмосфера ждут вас каждый день.",
    "keywords": [
      "кофе",
      "чай",
      "матча",
      "кафе",
      "Бишкек",
      "эспрессо",
      "латте",
      "капучино"
    ],
    "url": "https://coffee-k.netlify.app",
    "image": ""
  },
  "openGraph": {
    "title": "☕ Кофе и Чай - Ваше место для идеального напитка",
    "description": "Откройте для себя мир вкуса в нашем уютном кафе. Свежий кофе, ароматный чай и креативные матча-латте.",
    "image": "",
    "type": "website"
  },
  "twitter": {
    "title": "☕ Кофе и Чай - Лучшие напитки в Бишкеке",
    "description": "Насладитесь лучшим кофе, чаем и матча в городе Бишкек. Свежеобжаренные зерна и авторские рецепты.",
    "image": "",
    "card": "summary_large_image",
    "site": "@coffee_tea_kg"
  }
}
